<annotation>
	<folder>data</folder>
	<filename>127.jpeg</filename>
	<path>C:\Users\Ricard\Desktop\zellen\data\127.jpeg</path>
	<source>
		<database>Unknown</database>
	</source>
	<size>
		<width>256</width>
		<height>256</height>
		<depth>1</depth>
	</size>
	<segmented>0</segmented>
	<object>
		<name>individual</name>
		<pose>Unspecified</pose>
		<truncated>1</truncated>
		<difficult>0</difficult>
		<bndbox>
			<xmin>41</xmin>
			<ymin>1</ymin>
			<xmax>53</xmax>
			<ymax>6</ymax>
		</bndbox>
	</object>
	<object>
		<name>individual</name>
		<pose>Unspecified</pose>
		<truncated>0</truncated>
		<difficult>0</difficult>
		<bndbox>
			<xmin>45</xmin>
			<ymin>52</ymin>
			<xmax>55</xmax>
			<ymax>61</ymax>
		</bndbox>
	</object>
	<object>
		<name>individual</name>
		<pose>Unspecified</pose>
		<truncated>0</truncated>
		<difficult>0</difficult>
		<bndbox>
			<xmin>130</xmin>
			<ymin>57</ymin>
			<xmax>140</xmax>
			<ymax>69</ymax>
		</bndbox>
	</object>
	<object>
		<name>budding</name>
		<pose>Unspecified</pose>
		<truncated>0</truncated>
		<difficult>0</difficult>
		<bndbox>
			<xmin>49</xmin>
			<ymin>110</ymin>
			<xmax>67</xmax>
			<ymax>122</ymax>
		</bndbox>
	</object>
	<object>
		<name>budding</name>
		<pose>Unspecified</pose>
		<truncated>0</truncated>
		<difficult>0</difficult>
		<bndbox>
			<xmin>155</xmin>
			<ymin>57</ymin>
			<xmax>177</xmax>
			<ymax>71</ymax>
		</bndbox>
	</object>
	<object>
		<name>budding</name>
		<pose>Unspecified</pose>
		<truncated>0</truncated>
		<difficult>0</difficult>
		<bndbox>
			<xmin>47</xmin>
			<ymin>198</ymin>
			<xmax>65</xmax>
			<ymax>214</ymax>
		</bndbox>
	</object>
	<object>
		<name>budding</name>
		<pose>Unspecified</pose>
		<truncated>0</truncated>
		<difficult>0</difficult>
		<bndbox>
			<xmin>134</xmin>
			<ymin>178</ymin>
			<xmax>151</xmax>
			<ymax>201</ymax>
		</bndbox>
	</object>
</annotation>
